main.py
copper_rabbit/__init__.py
copper_rabbit/main.py
copper_rabbit/actions/Activity.py
copper_rabbit/actions/Request copy.py
copper_rabbit/actions/Request.py
copper_rabbit/actions/Session.py
copper_rabbit/actions/Token.py
copper_rabbit/actions/User.py
copper_rabbit/actions/__init__.py
copper_rabbit/custom_fields/CrudType.py
copper_rabbit/custom_fields/DeletedTimestamp.py
copper_rabbit/custom_fields/HashidPrimary.py
copper_rabbit/custom_fields/RequestLog.py
copper_rabbit/custom_fields/RequestMethod.py
copper_rabbit/custom_fields/StatusCode.py
copper_rabbit/custom_fields/__init__.py
copper_rabbit/decorators/__init__.py
copper_rabbit/decorators/jwt.py
copper_rabbit/models/Activity.py
copper_rabbit/models/Device.py
copper_rabbit/models/Request.py
copper_rabbit/models/Session.py
copper_rabbit/models/Token.py
copper_rabbit/models/User.py
copper_rabbit/models/__init__.py
copper_rabbit/schemas/Activity.py
copper_rabbit/schemas/Request.py
copper_rabbit/schemas/Session.py
copper_rabbit/schemas/Token.py
copper_rabbit/schemas/User.py
copper_rabbit/schemas/__init__.py
copper_rabbit/settings/__init__.py
copper_rabbit/settings/control.py
copper_rabbit/settings/datas.py
copper_rabbit/settings/globe.py
copper_rabbit/settings/types.py
copper_rabbit/support/BaseSchema.py
copper_rabbit/support/BlueprintMixin.py
copper_rabbit/support/Log.py
copper_rabbit/support/Result.py
copper_rabbit/support/__init__.py
copper_rabbit/support/actions.py
copper_rabbit/support/db_error_handling.py
copper_rabbit/support/filter.py
copper_rabbit/support/gen_mysql_connection_url.py
copper_rabbit/support/get_header_cookie.py
copper_rabbit/support/timestamp.py
colemen_copper_rabbit-0.4.7.dist-info/METADATA
colemen_copper_rabbit-0.4.7.dist-info/WHEEL
colemen_copper_rabbit-0.4.7.dist-info/top_level.txt
colemen_copper_rabbit-0.4.7.dist-info/RECORD
