Metadata-Version: 2.1
Name: colemen-copper-rabbit
Version: 0.4.7
Summary: copper_rabbit
Author: Colemen Atwood
Author-email: <atwoodcolemen@gmail.com>
Keywords: python
Classifier: Development Status :: 3 - Alpha
Classifier: Intended Audience :: Education
Classifier: Programming Language :: Python :: 2
Classifier: Programming Language :: Python :: 3
Classifier: Operating System :: MacOS :: MacOS X
Classifier: Operating System :: Microsoft :: Windows
Requires-Dist: colemen-utils
Requires-Dist: flask
Requires-Dist: pyjwt
Requires-Dist: passlib
Requires-Dist: sqlalchemy-utils
